LICENSE
MANIFEST.in
README.md
setup.cfg
setup.py
djangorest_openapi_utils/__init__.py
djangorest_openapi_utils/meta.py
djangorest_openapi_utils.egg-info/PKG-INFO
djangorest_openapi_utils.egg-info/SOURCES.txt
djangorest_openapi_utils.egg-info/dependency_links.txt
djangorest_openapi_utils.egg-info/requires.txt
djangorest_openapi_utils.egg-info/top_level.txt
djangorest_openapi_utils/openapi/__init__.py
djangorest_openapi_utils/openapi/constants.py
djangorest_openapi_utils/openapi/schemas.py
djangorest_openapi_utils/openapi/settings.py
djangorest_openapi_utils/openapi/urls.py
djangorest_openapi_utils/rapidoc/__init__.py
djangorest_openapi_utils/rapidoc/settings.py
djangorest_openapi_utils/rapidoc/urls.py
djangorest_openapi_utils/rapidoc/view.py
djangorest_openapi_utils/rapidoc/templates/rapidoc/rapidoc.html
djangorest_openapi_utils/redoc/__init__.py
djangorest_openapi_utils/redoc/settings.py
djangorest_openapi_utils/redoc/urls.py
djangorest_openapi_utils/redoc/view.py
djangorest_openapi_utils/redoc/templates/redoc/redoc.html
djangorest_openapi_utils/swagger/__init__.py
djangorest_openapi_utils/swagger/settings.py
djangorest_openapi_utils/swagger/urls.py
djangorest_openapi_utils/swagger/view.py
djangorest_openapi_utils/swagger/templates/swagger/swagger.html